Metadata-Version: 2.1
Name: gleb-pattern
Version: 0.1
Summary: Comic library for a friend
Author-email: nn@elros.ru
License-File: LICENSE
